paddle/__init__.py
paddle/_coupons.py
paddle/_licenses.py
paddle/_order_information.py
paddle/_pay_links.py
paddle/_payments.py
paddle/_plans.py
paddle/_prices.py
paddle/_products.py
paddle/_subscription_users.py
paddle/_transactions.py
paddle/_user_history.py
paddle/_webhooks.py
paddle/constants.py
paddle/paddle.py
paddle/types.py
paddle/validators.py
paddle_python-0.6.0.dist-info/LICENSE.md
paddle_python-0.6.0.dist-info/WHEEL
paddle_python-0.6.0.dist-info/METADATA
paddle_python-0.6.0.dist-info/RECORD
