Metadata-Version: 2.1
Name: paddle-python
Version: 0.6.0
Summary: Python wrapper around the Paddle.com API
Home-page: https://github.com/pyepye/paddle-python
License: MIT
Keywords: paddle,paddle.com,payments,billing,commerce,finance,saas
Author: Matt Pye
Author-email: pyematt@gmail.com
Requires-Python: >=3.5,<4.0
Classifier: License :: OSI Approved :: MIT License
Classifier: Programming Language :: Python :: 3
Classifier: Programming Language :: Python :: 3.5
Classifier: Programming Language :: Python :: 3.6
Classifier: Programming Language :: Python :: 3.7
Classifier: Programming Language :: Python :: 3.8
Requires-Dist: requests (>=2.23.0,<3.0.0)
Project-URL: Repository, https://github.com/pyepye/paddle-python
